[
	{
		"id": "0001",
		"path": "/data/img/01.jpg",
		"author": "Chris Abrams",
		"date": "June 5th, 2006",
		"tags": ["Chris", "Fifi"],
		"location": "Minneapolis, MS",
		"stars": "1",
		"colors": {
			"red": "1",
			"orange": "0",
			"yellow": "1",
			"green": "0",
			"blue": "1",
			"purple": "0"
		}
	},
	{
		"id": "0002",
		"path": "/data/img/02.jpg",
		"author": "Chris Abrams",
		"date": "June 5th, 2006",
		"tags": ["Chris"],
		"location": "Airplane",
		"stars": "2",
		"colors": {
			"red": "1",
			"orange": "1",
			"yellow": "1",
			"green": "0",
			"blue": "1",
			"purple": "0"
		}
	},
	{
		"id": "0003",
		"path": "/data/img/03.jpg",
		"author": "Chris Abrams",
		"date": "June 5th, 2006",
		"tags": ["Jennifer"],
		"location": "Minneapolis, MS",
		"stars": "3",
		"colors": {
			"red": "1",
			"orange": "0",
			"yellow": "0",
			"green": "0",
			"blue": "1",
			"purple": "0"
		}
	},
	{
		"id": "0004",
		"path": "/data/img/04.jpg",
		"author": "Chris Abrams",
		"date": "June 5th, 2006",
		"location": "Seoul, South Korea",
		"stars": "4",
		"colors": {
			"red": "0",
			"orange": "0",
			"yellow": "1",
			"green": "0",
			"blue": "1",
			"purple": "0"
		}
	},
	{
		"id": "0005",
		"path": "/data/img/05.jpg",
		"author": "Chris Abrams",
		"date": "June 5th, 2006",
		"location": "Seoul, South Korea",
		"stars": "5",
		"colors": {
			"red": "0",
			"orange": "0",
			"yellow": "1",
			"green": "0",
			"blue": "1",
			"purple": "1"
		}
	},
	{
		"id": "0006",
		"path": "/data/img/06.jpg",
		"author": "Chris Abrams",
		"date": "June 5th, 2006",
		"location": "Seoul, South Korea",
		"stars": "2",
		"colors": {
			"red": "1",
			"orange": "0",
			"yellow": "1",
			"green": "0",
			"blue": "1",
			"purple": "0"
		}
	},
	{
		"id": "0007",
		"path": "/data/img/07.jpg",
		"author": "Chris Abrams",
		"date": "June 5th, 2006",
		"location": "Seoul, South Korea",
		"stars": "4",
		"colors": {
			"red": "1",
			"orange": "1",
			"yellow": "1",
			"green": "0",
			"blue": "1",
			"purple": "1"
		}
	},
	{
		"id": "0008",
		"path": "/data/img/08.jpg",
		"author": "Chris Abrams",
		"date": "June 5th, 2006",
		"location": "Seoul, South Korea",
		"stars": "4",
		"colors": {
			"red": "0",
			"orange": "0",
			"yellow": "1",
			"green": "1",
			"blue": "0",
			"purple": "0"
		}
	},
	{
		"id": "0009",
		"path": "/data/img/09.jpg",
		"author": "Chris Abrams",
		"date": "June 5th, 2006",
		"location": "Seoul, South Korea",
		"stars": "5",
		"colors": {
			"red": "0",
			"orange": "0",
			"yellow": "0",
			"green": "1",
			"blue": "1",
			"purple": "1"
		}
	}
]